citation_finder.py
citation_finder-1.0.0.dist-info/METADATA
citation_finder-1.0.0.dist-info/WHEEL
citation_finder-1.0.0.dist-info/RECORD
